slf4py/__init__.py
slf4py/create_logger.py
slf4py/set_logger.py
slf4py-0.0.4.dist-info/METADATA
slf4py-0.0.4.dist-info/WHEEL
slf4py-0.0.4.dist-info/top_level.txt
slf4py-0.0.4.dist-info/RECORD
