Metadata-Version: 2.1
Name: slf4py
Version: 0.0.4
Summary: Simple Logging Facade for Python
Author: taiyo tamura
Author-email: gtaiyou24@gmail.com
